classes/__init__.py
classes/helper.py
easierexcel/__init__.py
easierexcel/excel.py
easierexcel/sheet.py
easierexcel/classes/__init__.py
easierexcel/classes/helper.py
test/__init__.py
test/test_excel.py
test/test_sheet.py
easierexcel-0.10.1.dist-info/LICENSE.txt
easierexcel-0.10.1.dist-info/METADATA
easierexcel-0.10.1.dist-info/WHEEL
easierexcel-0.10.1.dist-info/top_level.txt
easierexcel-0.10.1.dist-info/RECORD
