Metadata-Version: 2.1
Name: easierexcel
Version: 0.10.1
Summary: Easy viewing/editing of Excel Files
Home-page: https://github.com/Concrete18/easierexcel
Author: Concrete18
Author-email: <michaelericson19@gmail.com>
License: MIT
Keywords: excel
Classifier: Development Status :: 5 - Production/Stable
Classifier: Intended Audience :: Developers
Classifier: Operating System :: Microsoft :: Windows :: Windows 10
Classifier: License :: OSI Approved :: MIT License
Classifier: Programming Language :: Python :: 3
License-File: LICENSE.txt
Requires-Dist: openpyxl
Requires-Dist: pandas
